transitkit/__init__.py
transitkit/__main__.py
transitkit/__version__.py
transitkit/analysis.py
transitkit/cli.py
transitkit/core.py
transitkit/gui_app.py
transitkit/io.py
transitkit/models.py
transitkit/nea.py
transitkit/py.typed
transitkit/utils.py
transitkit/validation.py
transitkit/visualization.py
transitkit-2.0.2.dist-info/licenses/LICENSE
transitkit-2.0.2.dist-info/METADATA
transitkit-2.0.2.dist-info/WHEEL
transitkit-2.0.2.dist-info/entry_points.txt
transitkit-2.0.2.dist-info/top_level.txt
transitkit-2.0.2.dist-info/RECORD
