Metadata-Version: 2.4
Name: transitkit
Version: 2.0.2
Summary: Professional Exoplanet Transit Light Curve Analysis Toolkit
Author-email: Arif Solmaz <arif.solmaz@gmail.com>
License: MIT
Project-URL: Homepage, https://github.com/arifsolmaz/transitkit
Project-URL: Documentation, https://transitkit.readthedocs.io
Keywords: exoplanet,transit,photometry,astronomy,TESS,Kepler,BLS,TTV
Classifier: Development Status :: 4 - Beta
Classifier: Intended Audience :: Science/Research
Classifier: License :: OSI Approved :: MIT License
Classifier: Programming Language :: Python :: 3
Classifier: Programming Language :: Python :: 3.9
Classifier: Programming Language :: Python :: 3.10
Classifier: Programming Language :: Python :: 3.11
Classifier: Programming Language :: Python :: 3.12
Classifier: Topic :: Scientific/Engineering :: Astronomy
Requires-Python: >=3.9
License-File: LICENSE
Requires-Dist: numpy>=1.21
Requires-Dist: scipy>=1.8
Requires-Dist: matplotlib>=3.5
Requires-Dist: astropy>=5.1
Requires-Dist: lightkurve>=2.3
Requires-Dist: pandas>=1.4
Requires-Dist: scikit-learn>=1.0
Requires-Dist: seaborn>=0.12
Requires-Dist: h5py>=3.6
Requires-Dist: streamlit>=1.24
Provides-Extra: mcmc
Requires-Dist: emcee>=3.1; extra == "mcmc"
Requires-Dist: corner>=2.2; extra == "mcmc"
Provides-Extra: cli
Requires-Dist: click>=8.0; extra == "cli"
Requires-Dist: rich>=12.0; extra == "cli"
Provides-Extra: full
Requires-Dist: emcee>=3.1; extra == "full"
Requires-Dist: corner>=2.2; extra == "full"
Requires-Dist: batman-package>=2.4; extra == "full"
Requires-Dist: click>=8.0; extra == "full"
Requires-Dist: rich>=12.0; extra == "full"
Requires-Dist: h5py>=3.6; extra == "full"
Provides-Extra: dev
Requires-Dist: pytest>=7.0; extra == "dev"
Requires-Dist: pytest-cov>=4.0; extra == "dev"
Requires-Dist: black>=23.0; extra == "dev"
Requires-Dist: isort>=5.12; extra == "dev"
Requires-Dist: flake8>=6.0; extra == "dev"
Requires-Dist: mypy>=1.0; extra == "dev"
Requires-Dist: pre-commit>=3.0; extra == "dev"
Provides-Extra: docs
Requires-Dist: sphinx>=6.0; extra == "docs"
Requires-Dist: sphinx-rtd-theme>=1.2; extra == "docs"
Requires-Dist: myst-parser>=1.0; extra == "docs"
Requires-Dist: nbsphinx>=0.9; extra == "docs"
Requires-Dist: ipykernel; extra == "docs"
Dynamic: license-file
